cysgp4/__init__.py
cysgp4/_compiler.c
cysgp4/compiler_version.cpython-310-x86_64-linux-gnu.so
cysgp4/cysgp4.cpp
cysgp4/cysgp4.cpython-310-x86_64-linux-gnu.so
cysgp4/cysgp4.pxd
cysgp4/cysgp4.pyx
cysgp4/helpers.py
cysgp4/init_testrunner.py
cysgp4/setup_package.py
cysgp4/utils.cpp
cysgp4/utils.cpython-310-x86_64-linux-gnu.so
cysgp4/utils.pxd
cysgp4/utils.pyx
cysgp4/version.py
cysgp4/tests/__init__.py
cysgp4/tests/conftest.py
cysgp4/tests/test_cysgp4.py
cysgp4/tests/test_utils.py
cysgp4/tests/data/science.txt
cysgp4.libs/libgomp-24e2ab19.so.1.0.0
cysgp4-0.4.0.dist-info/COPYING.Apache2
cysgp4-0.4.0.dist-info/COPYING.GPLv3.txt
cysgp4-0.4.0.dist-info/METADATA
cysgp4-0.4.0.dist-info/TEMPLATE_LICENCE.rst
cysgp4-0.4.0.dist-info/WHEEL
cysgp4-0.4.0.dist-info/top_level.txt
cysgp4-0.4.0.dist-info/RECORD
