Metadata-Version: 2.2
Name: cysgp4
Version: 0.4.0
Summary: cysgp4: a wrapper around the SGP4 package, for sat TLE calculations
Author-email: Benjamin Winkel <bwinkel@mpifr.de>
License: GPLv3
Project-URL: Homepage, https://pypi.org/project/cysgp4/
Project-URL: Documentation, https://bwinkel.github.io/cysgp4/
Project-URL: Repository, https://github.com/bwinkel/cysgp4
Project-URL: Issues, https://github.com/bwinkel/cysgp4/issues
Project-URL: Changelog, https://github.com/bwinkel/cysgp4/CHANGES.rst
Keywords: astronomy,science
Classifier: Intended Audience :: Science/Research
Classifier: Development Status :: 4 - Beta
Classifier: Operating System :: OS Independent
Classifier: License :: OSI Approved :: GNU General Public License v3 (GPLv3)
Classifier: License :: OSI Approved :: Apache Software License
Classifier: License :: OSI Approved :: BSD License
Classifier: Programming Language :: C++
Classifier: Programming Language :: Cython
Classifier: Programming Language :: Python :: 3 :: Only
Classifier: Programming Language :: Python :: Implementation :: CPython
Classifier: Topic :: Scientific/Engineering :: Astronomy
Requires-Python: >=3.10
License-File: COPYING.Apache2
License-File: COPYING.GPLv3.txt
License-File: TEMPLATE_LICENCE.rst
Requires-Dist: astropy
Requires-Dist: numpy
Requires-Dist: scipy
Requires-Dist: sgp4
Provides-Extra: test
Requires-Dist: pytest>=7.0; extra == "test"
Requires-Dist: pytest-astropy>=0.10; extra == "test"
Requires-Dist: pytest-doctestplus; extra == "test"
Requires-Dist: pytest-remotedata; extra == "test"
Provides-Extra: docs
Requires-Dist: sphinx; extra == "docs"
Requires-Dist: sphinx-astropy[confv2]; extra == "docs"
Requires-Dist: sphinx-copybutton; extra == "docs"
Requires-Dist: pydata-sphinx-theme; extra == "docs"
Requires-Dist: pytest>=7.0; extra == "docs"
